waves_python/__init__.py
waves_python/account/__init__.py
waves_python/account/address.py
waves_python/account/private_key.py
waves_python/account/public_key.py
waves_python/api/__init__.py
waves_python/api/node.py
waves_python/api/profile.py
waves_python/common/ByteString.py
waves_python/common/__init__.py
waves_python/common/alias.py
waves_python/common/asset_id.py
waves_python/common/base58_string.py
waves_python/common/base64_string.py
waves_python/common/exceptions.py
waves_python/common/id.py
waves_python/model/__init__.py
waves_python/model/application_status.py
waves_python/model/asset_balance.py
waves_python/model/asset_details.py
waves_python/model/block.py
waves_python/model/block_headers.py
waves_python/model/blockchain_rewards.py
waves_python/model/history_balance.py
waves_python/model/lease_info.py
waves_python/model/lease_status.py
waves_python/model/node_model.py
waves_python/model/script_details.py
waves_python/model/status.py
waves_python/model/votes.py
waves_python/transaction/__init__.py
waves_python/transaction/burn_transaction.py
waves_python/transaction/create_alias_transaction.py
waves_python/transaction/data_transaction.py
waves_python/transaction/exchange_transaction.py
waves_python/transaction/genesis_transaction.py
waves_python/transaction/invoke_script_transaction.py
waves_python/transaction/issue_transaction.py
waves_python/transaction/lease_cancel_transaction.py
waves_python/transaction/lease_transaction.py
waves_python/transaction/mass_transfer_transaction.py
waves_python/transaction/reissue_transaction.py
waves_python/transaction/set_asset_script_transaction.py
waves_python/transaction/set_script_transaction.py
waves_python/transaction/sponsor_fee_transaction.py
waves_python/transaction/transaction.py
waves_python/transaction/transaction_info.py
waves_python/transaction/transaction_or_order.py
waves_python/transaction/transaction_with_status.py
waves_python/transaction/transfer_transaction.py
waves_python-1.0.1.dist-info/LICENSE
waves_python-1.0.1.dist-info/METADATA
waves_python-1.0.1.dist-info/WHEEL
waves_python-1.0.1.dist-info/top_level.txt
waves_python-1.0.1.dist-info/RECORD
