Metadata-Version: 2.1
Name: waves-python
Version: 1.0.1
Summary: Python library for interacting with the Waves blockchain.
Home-page: https://github.com/wavesplatform/waves-python
Author: Dmitry Rozhaev
Author-email: admin@waveslabs.com
License: UNKNOWN
Platform: UNKNOWN
License-File: LICENSE
Requires-Dist: requests
Requires-Dist: base58
Requires-Dist: dataclasses-json
